<annotation>
    <folder>VOC2007</folder>
    <filename>03CF22F1.jpg</filename>
    <size>
        <width>2666</width>
        <height>2000</height>
        <depth>3</depth>
    </size>
    <object>
        <name>rebar</name>
        <pose>Unspecified</pose>
        <truncated>0</truncated>
        <difficult>0</difficult>
        <bndbox>
            <xmin>650</xmin>
            <ymin>159</ymin>
            <xmax>908</xmax>
            <ymax>406</ymax>
        </bndbox>
    </object>
    <object>
        <name>rebar</name>
        <pose>Unspecified</pose>
        <truncated>0</truncated>
        <difficult>0</difficult>
        <bndbox>
            <xmin>946</xmin>
            <ymin>154</ymin>
            <xmax>1184</xmax>
            <ymax>396</ymax>
        </bndbox>
    </object>
    <object>
        <name>rebar</name>
        <pose>Unspecified</pose>
        <truncated>0</truncated>
        <difficult>0</difficult>
        <bndbox>
            <xmin>288</xmin>
            <ymin>336</ymin>
            <xmax>552</xmax>
            <ymax>546</ymax>
        </bndbox>
    </object>
    <object>
        <name>rebar</name>
        <pose>Unspecified</pose>
        <truncated>0</truncated>
        <difficult>0</difficult>
        <bndbox>
            <xmin>596</xmin>
            <ymin>408</ymin>
            <xmax>834</xmax>
            <ymax>613</ymax>
        </bndbox>
    </object>
    <object>
        <name>rebar</name>
        <pose>Unspecified</pose>
        <truncated>0</truncated>
        <difficult>0</difficult>
        <bndbox>
            <xmin>798</xmin>
            <ymin>300</ymin>
            <xmax>1024</xmax>
            <ymax>540</ymax>
        </bndbox>
    </object>
    <object>
        <name>rebar</name>
        <pose>Unspecified</pose>
        <truncated>0</truncated>
        <difficult>0</difficult>
        <bndbox>
            <xmin>1100</xmin>
            <ymin>330</ymin>
            <xmax>1352</xmax>
            <ymax>570</ymax>
        </bndbox>
    </object>
    <object>
        <name>rebar</name>
        <pose>Unspecified</pose>
        <truncated>0</truncated>
        <difficult>0</difficult>
        <bndbox>
            <xmin>1322</xmin>
            <ymin>253</ymin>
            <xmax>1575</xmax>
            <ymax>517</ymax>
        </bndbox>
    </object>
    <object>
        <name>rebar</name>
        <pose>Unspecified</pose>
        <truncated>0</truncated>
        <difficult>0</difficult>
        <bndbox>
            <xmin>1546</xmin>
            <ymin>333</ymin>
            <xmax>1772</xmax>
            <ymax>533</ymax>
        </bndbox>
    </object>
    <object>
        <name>rebar</name>
        <pose>Unspecified</pose>
        <truncated>0</truncated>
        <difficult>0</difficult>
        <bndbox>
            <xmin>1766</xmin>
            <ymin>408</ymin>
            <xmax>2010</xmax>
            <ymax>618</ymax>
        </bndbox>
    </object>
    <object>
        <name>rebar</name>
        <pose>Unspecified</pose>
        <truncated>0</truncated>
        <difficult>0</difficult>
        <bndbox>
            <xmin>307</xmin>
            <ymin>574</ymin>
            <xmax>536</xmax>
            <ymax>798</ymax>
        </bndbox>
    </object>
    <object>
        <name>rebar</name>
        <pose>Unspecified</pose>
        <truncated>0</truncated>
        <difficult>0</difficult>
        <bndbox>
            <xmin>715</xmin>
            <ymin>502</ymin>
            <xmax>949</xmax>
            <ymax>760</ymax>
        </bndbox>
    </object>
    <object>
        <name>rebar</name>
        <pose>Unspecified</pose>
        <truncated>0</truncated>
        <difficult>0</difficult>
        <bndbox>
            <xmin>538</xmin>
            <ymin>636</ymin>
            <xmax>766</xmax>
            <ymax>881</ymax>
        </bndbox>
    </object>
    <object>
        <name>rebar</name>
        <pose>Unspecified</pose>
        <truncated>0</truncated>
        <difficult>0</difficult>
        <bndbox>
            <xmin>958</xmin>
            <ymin>512</ymin>
            <xmax>1219</xmax>
            <ymax>754</ymax>
        </bndbox>
    </object>
    <object>
        <name>rebar</name>
        <pose>Unspecified</pose>
        <truncated>0</truncated>
        <difficult>0</difficult>
        <bndbox>
            <xmin>1310</xmin>
            <ymin>465</ymin>
            <xmax>1530</xmax>
            <ymax>725</ymax>
        </bndbox>
    </object>
    <object>
        <name>rebar</name>
        <pose>Unspecified</pose>
        <truncated>0</truncated>
        <difficult>0</difficult>
        <bndbox>
            <xmin>1522</xmin>
            <ymin>496</ymin>
            <xmax>1774</xmax>
            <ymax>732</ymax>
        </bndbox>
    </object>
    <object>
        <name>rebar</name>
        <pose>Unspecified</pose>
        <truncated>0</truncated>
        <difficult>0</difficult>
        <bndbox>
            <xmin>1759</xmin>
            <ymin>600</ymin>
            <xmax>2018</xmax>
            <ymax>821</ymax>
        </bndbox>
    </object>
    <object>
        <name>rebar</name>
        <pose>Unspecified</pose>
        <truncated>0</truncated>
        <difficult>0</difficult>
        <bndbox>
            <xmin>317</xmin>
            <ymin>784</ymin>
            <xmax>538</xmax>
            <ymax>1034</ymax>
        </bndbox>
    </object>
    <object>
        <name>rebar</name>
        <pose>Unspecified</pose>
        <truncated>0</truncated>
        <difficult>0</difficult>
        <bndbox>
            <xmin>226</xmin>
            <ymin>998</ymin>
            <xmax>452</xmax>
            <ymax>1239</ymax>
        </bndbox>
    </object>
    <object>
        <name>rebar</name>
        <pose>Unspecified</pose>
        <truncated>0</truncated>
        <difficult>0</difficult>
        <bndbox>
            <xmin>393</xmin>
            <ymin>1086</ymin>
            <xmax>644</xmax>
            <ymax>1326</ymax>
        </bndbox>
    </object>
    <object>
        <name>rebar</name>
        <pose>Unspecified</pose>
        <truncated>0</truncated>
        <difficult>0</difficult>
        <bndbox>
            <xmin>530</xmin>
            <ymin>938</ymin>
            <xmax>762</xmax>
            <ymax>1175</ymax>
        </bndbox>
    </object>
    <object>
        <name>rebar</name>
        <pose>Unspecified</pose>
        <truncated>0</truncated>
        <difficult>0</difficult>
        <bndbox>
            <xmin>670</xmin>
            <ymin>1074</ymin>
            <xmax>896</xmax>
            <ymax>1306</ymax>
        </bndbox>
    </object>
    <object>
        <name>rebar</name>
        <pose>Unspecified</pose>
        <truncated>0</truncated>
        <difficult>0</difficult>
        <bndbox>
            <xmin>722</xmin>
            <ymin>769</ymin>
            <xmax>920</xmax>
            <ymax>1008</ymax>
        </bndbox>
    </object>
    <object>
        <name>rebar</name>
        <pose>Unspecified</pose>
        <truncated>0</truncated>
        <difficult>0</difficult>
        <bndbox>
            <xmin>827</xmin>
            <ymin>969</ymin>
            <xmax>1071</xmax>
            <ymax>1186</ymax>
        </bndbox>
    </object>
    <object>
        <name>rebar</name>
        <pose>Unspecified</pose>
        <truncated>0</truncated>
        <difficult>0</difficult>
        <bndbox>
            <xmin>870</xmin>
            <ymin>1236</ymin>
            <xmax>1094</xmax>
            <ymax>1437</ymax>
        </bndbox>
    </object>
    <object>
        <name>rebar</name>
        <pose>Unspecified</pose>
        <truncated>0</truncated>
        <difficult>0</difficult>
        <bndbox>
            <xmin>866</xmin>
            <ymin>1448</ymin>
            <xmax>1088</xmax>
            <ymax>1707</ymax>
        </bndbox>
    </object>
    <object>
        <name>rebar</name>
        <pose>Unspecified</pose>
        <truncated>0</truncated>
        <difficult>0</difficult>
        <bndbox>
            <xmin>1042</xmin>
            <ymin>1569</ymin>
            <xmax>1280</xmax>
            <ymax>1778</ymax>
        </bndbox>
    </object>
    <object>
        <name>rebar</name>
        <pose>Unspecified</pose>
        <truncated>0</truncated>
        <difficult>0</difficult>
        <bndbox>
            <xmin>1270</xmin>
            <ymin>1688</ymin>
            <xmax>1466</xmax>
            <ymax>1908</ymax>
        </bndbox>
    </object>
    <object>
        <name>rebar</name>
        <pose>Unspecified</pose>
        <truncated>0</truncated>
        <difficult>0</difficult>
        <bndbox>
            <xmin>1436</xmin>
            <ymin>1732</ymin>
            <xmax>1671</xmax>
            <ymax>1985</ymax>
        </bndbox>
    </object>
    <object>
        <name>rebar</name>
        <pose>Unspecified</pose>
        <truncated>0</truncated>
        <difficult>0</difficult>
        <bndbox>
            <xmin>1250</xmin>
            <ymin>1411</ymin>
            <xmax>1460</xmax>
            <ymax>1663</ymax>
        </bndbox>
    </object>
    <object>
        <name>rebar</name>
        <pose>Unspecified</pose>
        <truncated>0</truncated>
        <difficult>0</difficult>
        <bndbox>
            <xmin>1106</xmin>
            <ymin>1237</ymin>
            <xmax>1336</xmax>
            <ymax>1474</ymax>
        </bndbox>
    </object>
    <object>
        <name>rebar</name>
        <pose>Unspecified</pose>
        <truncated>0</truncated>
        <difficult>0</difficult>
        <bndbox>
            <xmin>834</xmin>
            <ymin>974</ymin>
            <xmax>1074</xmax>
            <ymax>1184</ymax>
        </bndbox>
    </object>
    <object>
        <name>rebar</name>
        <pose>Unspecified</pose>
        <truncated>0</truncated>
        <difficult>0</difficult>
        <bndbox>
            <xmin>1013</xmin>
            <ymin>1056</ymin>
            <xmax>1245</xmax>
            <ymax>1274</ymax>
        </bndbox>
    </object>
    <object>
        <name>rebar</name>
        <pose>Unspecified</pose>
        <truncated>0</truncated>
        <difficult>0</difficult>
        <bndbox>
            <xmin>958</xmin>
            <ymin>764</ymin>
            <xmax>1193</xmax>
            <ymax>984</ymax>
        </bndbox>
    </object>
    <object>
        <name>rebar</name>
        <pose>Unspecified</pose>
        <truncated>0</truncated>
        <difficult>0</difficult>
        <bndbox>
            <xmin>1126</xmin>
            <ymin>689</ymin>
            <xmax>1374</xmax>
            <ymax>926</ymax>
        </bndbox>
    </object>
    <object>
        <name>rebar</name>
        <pose>Unspecified</pose>
        <truncated>0</truncated>
        <difficult>0</difficult>
        <bndbox>
            <xmin>1108</xmin>
            <ymin>886</ymin>
            <xmax>1346</xmax>
            <ymax>1104</ymax>
        </bndbox>
    </object>
    <object>
        <name>rebar</name>
        <pose>Unspecified</pose>
        <truncated>0</truncated>
        <difficult>0</difficult>
        <bndbox>
            <xmin>1369</xmin>
            <ymin>726</ymin>
            <xmax>1586</xmax>
            <ymax>943</ymax>
        </bndbox>
    </object>
    <object>
        <name>rebar</name>
        <pose>Unspecified</pose>
        <truncated>0</truncated>
        <difficult>0</difficult>
        <bndbox>
            <xmin>1582</xmin>
            <ymin>733</ymin>
            <xmax>1822</xmax>
            <ymax>946</ymax>
        </bndbox>
    </object>
    <object>
        <name>rebar</name>
        <pose>Unspecified</pose>
        <truncated>0</truncated>
        <difficult>0</difficult>
        <bndbox>
            <xmin>1356</xmin>
            <ymin>940</ymin>
            <xmax>1593</xmax>
            <ymax>1172</ymax>
        </bndbox>
    </object>
    <object>
        <name>rebar</name>
        <pose>Unspecified</pose>
        <truncated>0</truncated>
        <difficult>0</difficult>
        <bndbox>
            <xmin>1256</xmin>
            <ymin>1149</ymin>
            <xmax>1507</xmax>
            <ymax>1366</ymax>
        </bndbox>
    </object>
    <object>
        <name>rebar</name>
        <pose>Unspecified</pose>
        <truncated>0</truncated>
        <difficult>0</difficult>
        <bndbox>
            <xmin>1430</xmin>
            <ymin>1349</ymin>
            <xmax>1655</xmax>
            <ymax>1586</ymax>
        </bndbox>
    </object>
    <object>
        <name>rebar</name>
        <pose>Unspecified</pose>
        <truncated>0</truncated>
        <difficult>0</difficult>
        <bndbox>
            <xmin>1585</xmin>
            <ymin>1532</ymin>
            <xmax>1803</xmax>
            <ymax>1785</ymax>
        </bndbox>
    </object>
    <object>
        <name>rebar</name>
        <pose>Unspecified</pose>
        <truncated>0</truncated>
        <difficult>0</difficult>
        <bndbox>
            <xmin>1700</xmin>
            <ymin>1702</ymin>
            <xmax>1964</xmax>
            <ymax>1922</ymax>
        </bndbox>
    </object>
    <object>
        <name>rebar</name>
        <pose>Unspecified</pose>
        <truncated>0</truncated>
        <difficult>0</difficult>
        <bndbox>
            <xmin>1956</xmin>
            <ymin>1714</ymin>
            <xmax>2159</xmax>
            <ymax>1940</ymax>
        </bndbox>
    </object>
    <object>
        <name>rebar</name>
        <pose>Unspecified</pose>
        <truncated>0</truncated>
        <difficult>0</difficult>
        <bndbox>
            <xmin>2167</xmin>
            <ymin>1560</ymin>
            <xmax>2403</xmax>
            <ymax>1800</ymax>
        </bndbox>
    </object>
    <object>
        <name>rebar</name>
        <pose>Unspecified</pose>
        <truncated>0</truncated>
        <difficult>0</difficult>
        <bndbox>
            <xmin>1948</xmin>
            <ymin>1512</ymin>
            <xmax>2180</xmax>
            <ymax>1712</ymax>
        </bndbox>
    </object>
    <object>
        <name>rebar</name>
        <pose>Unspecified</pose>
        <truncated>0</truncated>
        <difficult>0</difficult>
        <bndbox>
            <xmin>1728</xmin>
            <ymin>1413</ymin>
            <xmax>1954</xmax>
            <ymax>1644</ymax>
        </bndbox>
    </object>
    <object>
        <name>rebar</name>
        <pose>Unspecified</pose>
        <truncated>0</truncated>
        <difficult>0</difficult>
        <bndbox>
            <xmin>1506</xmin>
            <ymin>1126</ymin>
            <xmax>1725</xmax>
            <ymax>1375</ymax>
        </bndbox>
    </object>
    <object>
        <name>rebar</name>
        <pose>Unspecified</pose>
        <truncated>0</truncated>
        <difficult>0</difficult>
        <bndbox>
            <xmin>1722</xmin>
            <ymin>1134</ymin>
            <xmax>1940</xmax>
            <ymax>1382</ymax>
        </bndbox>
    </object>
    <object>
        <name>rebar</name>
        <pose>Unspecified</pose>
        <truncated>0</truncated>
        <difficult>0</difficult>
        <bndbox>
            <xmin>2053</xmin>
            <ymin>1271</ymin>
            <xmax>2273</xmax>
            <ymax>1492</ymax>
        </bndbox>
    </object>
    <object>
        <name>rebar</name>
        <pose>Unspecified</pose>
        <truncated>0</truncated>
        <difficult>0</difficult>
        <bndbox>
            <xmin>2299</xmin>
            <ymin>1330</ymin>
            <xmax>2540</xmax>
            <ymax>1558</ymax>
        </bndbox>
    </object>
    <object>
        <name>rebar</name>
        <pose>Unspecified</pose>
        <truncated>0</truncated>
        <difficult>0</difficult>
        <bndbox>
            <xmin>1558</xmin>
            <ymin>926</ymin>
            <xmax>1786</xmax>
            <ymax>1174</ymax>
        </bndbox>
    </object>
    <object>
        <name>rebar</name>
        <pose>Unspecified</pose>
        <truncated>0</truncated>
        <difficult>0</difficult>
        <bndbox>
            <xmin>1890</xmin>
            <ymin>551</ymin>
            <xmax>2088</xmax>
            <ymax>740</ymax>
        </bndbox>
    </object>
    <object>
        <name>rebar</name>
        <pose>Unspecified</pose>
        <truncated>0</truncated>
        <difficult>0</difficult>
        <bndbox>
            <xmin>2141</xmin>
            <ymin>486</ymin>
            <xmax>2364</xmax>
            <ymax>689</ymax>
        </bndbox>
    </object>
    <object>
        <name>rebar</name>
        <pose>Unspecified</pose>
        <truncated>0</truncated>
        <difficult>0</difficult>
        <bndbox>
            <xmin>1914</xmin>
            <ymin>743</ymin>
            <xmax>2140</xmax>
            <ymax>948</ymax>
        </bndbox>
    </object>
    <object>
        <name>rebar</name>
        <pose>Unspecified</pose>
        <truncated>0</truncated>
        <difficult>0</difficult>
        <bndbox>
            <xmin>1793</xmin>
            <ymin>899</ymin>
            <xmax>2027</xmax>
            <ymax>1138</ymax>
        </bndbox>
    </object>
    <object>
        <name>rebar</name>
        <pose>Unspecified</pose>
        <truncated>0</truncated>
        <difficult>0</difficult>
        <bndbox>
            <xmin>1934</xmin>
            <ymin>1062</ymin>
            <xmax>2200</xmax>
            <ymax>1300</ymax>
        </bndbox>
    </object>
    <object>
        <name>rebar</name>
        <pose>Unspecified</pose>
        <truncated>0</truncated>
        <difficult>0</difficult>
        <bndbox>
            <xmin>2138</xmin>
            <ymin>689</ymin>
            <xmax>2369</xmax>
            <ymax>920</ymax>
        </bndbox>
    </object>
    <object>
        <name>rebar</name>
        <pose>Unspecified</pose>
        <truncated>0</truncated>
        <difficult>0</difficult>
        <bndbox>
            <xmin>2091</xmin>
            <ymin>960</ymin>
            <xmax>2346</xmax>
            <ymax>1169</ymax>
        </bndbox>
    </object>
    <object>
        <name>rebar</name>
        <pose>Unspecified</pose>
        <truncated>0</truncated>
        <difficult>0</difficult>
        <bndbox>
            <xmin>2325</xmin>
            <ymin>880</ymin>
            <xmax>2586</xmax>
            <ymax>1122</ymax>
        </bndbox>
    </object>
    <object>
        <name>rebar</name>
        <pose>Unspecified</pose>
        <truncated>0</truncated>
        <difficult>0</difficult>
        <bndbox>
            <xmin>2326</xmin>
            <ymin>1115</ymin>
            <xmax>2556</xmax>
            <ymax>1343</ymax>
        </bndbox>
    </object>
</annotation>