<annotation>
    <folder>VOC2007</folder>
    <filename>99E783B2.jpg</filename>
    <size>
        <width>2666</width>
        <height>2000</height>
        <depth>3</depth>
    </size>
    <object>
        <name>rebar</name>
        <pose>Unspecified</pose>
        <truncated>0</truncated>
        <difficult>0</difficult>
        <bndbox>
            <xmin>180</xmin>
            <ymin>656</ymin>
            <xmax>390</xmax>
            <ymax>846</ymax>
        </bndbox>
    </object>
    <object>
        <name>rebar</name>
        <pose>Unspecified</pose>
        <truncated>0</truncated>
        <difficult>0</difficult>
        <bndbox>
            <xmin>259</xmin>
            <ymin>528</ymin>
            <xmax>469</xmax>
            <ymax>716</ymax>
        </bndbox>
    </object>
    <object>
        <name>rebar</name>
        <pose>Unspecified</pose>
        <truncated>0</truncated>
        <difficult>0</difficult>
        <bndbox>
            <xmin>435</xmin>
            <ymin>721</ymin>
            <xmax>600</xmax>
            <ymax>887</ymax>
        </bndbox>
    </object>
    <object>
        <name>rebar</name>
        <pose>Unspecified</pose>
        <truncated>0</truncated>
        <difficult>0</difficult>
        <bndbox>
            <xmin>544</xmin>
            <ymin>828</ymin>
            <xmax>710</xmax>
            <ymax>999</ymax>
        </bndbox>
    </object>
    <object>
        <name>rebar</name>
        <pose>Unspecified</pose>
        <truncated>0</truncated>
        <difficult>0</difficult>
        <bndbox>
            <xmin>570</xmin>
            <ymin>637</ymin>
            <xmax>760</xmax>
            <ymax>810</ymax>
        </bndbox>
    </object>
    <object>
        <name>rebar</name>
        <pose>Unspecified</pose>
        <truncated>0</truncated>
        <difficult>0</difficult>
        <bndbox>
            <xmin>498</xmin>
            <ymin>398</ymin>
            <xmax>693</xmax>
            <ymax>589</ymax>
        </bndbox>
    </object>
    <object>
        <name>rebar</name>
        <pose>Unspecified</pose>
        <truncated>0</truncated>
        <difficult>0</difficult>
        <bndbox>
            <xmin>715</xmin>
            <ymin>377</ymin>
            <xmax>913</xmax>
            <ymax>577</ymax>
        </bndbox>
    </object>
    <object>
        <name>rebar</name>
        <pose>Unspecified</pose>
        <truncated>0</truncated>
        <difficult>0</difficult>
        <bndbox>
            <xmin>875</xmin>
            <ymin>294</ymin>
            <xmax>1055</xmax>
            <ymax>492</ymax>
        </bndbox>
    </object>
    <object>
        <name>rebar</name>
        <pose>Unspecified</pose>
        <truncated>0</truncated>
        <difficult>0</difficult>
        <bndbox>
            <xmin>985</xmin>
            <ymin>473</ymin>
            <xmax>1162</xmax>
            <ymax>656</ymax>
        </bndbox>
    </object>
    <object>
        <name>rebar</name>
        <pose>Unspecified</pose>
        <truncated>0</truncated>
        <difficult>0</difficult>
        <bndbox>
            <xmin>1147</xmin>
            <ymin>376</ymin>
            <xmax>1296</xmax>
            <ymax>554</ymax>
        </bndbox>
    </object>
    <object>
        <name>rebar</name>
        <pose>Unspecified</pose>
        <truncated>0</truncated>
        <difficult>0</difficult>
        <bndbox>
            <xmin>1159</xmin>
            <ymin>548</ymin>
            <xmax>1332</xmax>
            <ymax>726</ymax>
        </bndbox>
    </object>
    <object>
        <name>rebar</name>
        <pose>Unspecified</pose>
        <truncated>0</truncated>
        <difficult>0</difficult>
        <bndbox>
            <xmin>1325</xmin>
            <ymin>680</ymin>
            <xmax>1538</xmax>
            <ymax>878</ymax>
        </bndbox>
    </object>
    <object>
        <name>rebar</name>
        <pose>Unspecified</pose>
        <truncated>0</truncated>
        <difficult>0</difficult>
        <bndbox>
            <xmin>1419</xmin>
            <ymin>570</ymin>
            <xmax>1578</xmax>
            <ymax>733</ymax>
        </bndbox>
    </object>
    <object>
        <name>rebar</name>
        <pose>Unspecified</pose>
        <truncated>0</truncated>
        <difficult>0</difficult>
        <bndbox>
            <xmin>1405</xmin>
            <ymin>357</ymin>
            <xmax>1586</xmax>
            <ymax>564</ymax>
        </bndbox>
    </object>
    <object>
        <name>rebar</name>
        <pose>Unspecified</pose>
        <truncated>0</truncated>
        <difficult>0</difficult>
        <bndbox>
            <xmin>1547</xmin>
            <ymin>410</ymin>
            <xmax>1687</xmax>
            <ymax>605</ymax>
        </bndbox>
    </object>
    <object>
        <name>rebar</name>
        <pose>Unspecified</pose>
        <truncated>0</truncated>
        <difficult>0</difficult>
        <bndbox>
            <xmin>1653</xmin>
            <ymin>420</ymin>
            <xmax>1822</xmax>
            <ymax>612</ymax>
        </bndbox>
    </object>
    <object>
        <name>rebar</name>
        <pose>Unspecified</pose>
        <truncated>0</truncated>
        <difficult>0</difficult>
        <bndbox>
            <xmin>1784</xmin>
            <ymin>398</ymin>
            <xmax>1950</xmax>
            <ymax>560</ymax>
        </bndbox>
    </object>
    <object>
        <name>rebar</name>
        <pose>Unspecified</pose>
        <truncated>0</truncated>
        <difficult>0</difficult>
        <bndbox>
            <xmin>1788</xmin>
            <ymin>569</ymin>
            <xmax>1979</xmax>
            <ymax>728</ymax>
        </bndbox>
    </object>
    <object>
        <name>rebar</name>
        <pose>Unspecified</pose>
        <truncated>0</truncated>
        <difficult>0</difficult>
        <bndbox>
            <xmin>1561</xmin>
            <ymin>600</ymin>
            <xmax>1711</xmax>
            <ymax>762</ymax>
        </bndbox>
    </object>
    <object>
        <name>rebar</name>
        <pose>Unspecified</pose>
        <truncated>0</truncated>
        <difficult>0</difficult>
        <bndbox>
            <xmin>1636</xmin>
            <ymin>627</ymin>
            <xmax>1771</xmax>
            <ymax>786</ymax>
        </bndbox>
    </object>
    <object>
        <name>rebar</name>
        <pose>Unspecified</pose>
        <truncated>0</truncated>
        <difficult>0</difficult>
        <bndbox>
            <xmin>1756</xmin>
            <ymin>723</ymin>
            <xmax>1921</xmax>
            <ymax>854</ymax>
        </bndbox>
    </object>
    <object>
        <name>rebar</name>
        <pose>Unspecified</pose>
        <truncated>0</truncated>
        <difficult>0</difficult>
        <bndbox>
            <xmin>1921</xmin>
            <ymin>736</ymin>
            <xmax>2080</xmax>
            <ymax>902</ymax>
        </bndbox>
    </object>
    <object>
        <name>rebar</name>
        <pose>Unspecified</pose>
        <truncated>0</truncated>
        <difficult>0</difficult>
        <bndbox>
            <xmin>2027</xmin>
            <ymin>574</ymin>
            <xmax>2184</xmax>
            <ymax>704</ymax>
        </bndbox>
    </object>
    <object>
        <name>rebar</name>
        <pose>Unspecified</pose>
        <truncated>0</truncated>
        <difficult>0</difficult>
        <bndbox>
            <xmin>2070</xmin>
            <ymin>695</ymin>
            <xmax>2210</xmax>
            <ymax>839</ymax>
        </bndbox>
    </object>
    <object>
        <name>rebar</name>
        <pose>Unspecified</pose>
        <truncated>0</truncated>
        <difficult>0</difficult>
        <bndbox>
            <xmin>2097</xmin>
            <ymin>822</ymin>
            <xmax>2229</xmax>
            <ymax>953</ymax>
        </bndbox>
    </object>
    <object>
        <name>rebar</name>
        <pose>Unspecified</pose>
        <truncated>0</truncated>
        <difficult>0</difficult>
        <bndbox>
            <xmin>2065</xmin>
            <ymin>383</ymin>
            <xmax>2254</xmax>
            <ymax>574</ymax>
        </bndbox>
    </object>
    <object>
        <name>rebar</name>
        <pose>Unspecified</pose>
        <truncated>0</truncated>
        <difficult>0</difficult>
        <bndbox>
            <xmin>2179</xmin>
            <ymin>528</ymin>
            <xmax>2314</xmax>
            <ymax>685</ymax>
        </bndbox>
    </object>
    <object>
        <name>rebar</name>
        <pose>Unspecified</pose>
        <truncated>0</truncated>
        <difficult>0</difficult>
        <bndbox>
            <xmin>2196</xmin>
            <ymin>641</ymin>
            <xmax>2307</xmax>
            <ymax>784</ymax>
        </bndbox>
    </object>
    <object>
        <name>rebar</name>
        <pose>Unspecified</pose>
        <truncated>0</truncated>
        <difficult>0</difficult>
        <bndbox>
            <xmin>811</xmin>
            <ymin>550</ymin>
            <xmax>976</xmax>
            <ymax>733</ymax>
        </bndbox>
    </object>
    <object>
        <name>rebar</name>
        <pose>Unspecified</pose>
        <truncated>0</truncated>
        <difficult>0</difficult>
        <bndbox>
            <xmin>1009</xmin>
            <ymin>663</ymin>
            <xmax>1173</xmax>
            <ymax>825</ymax>
        </bndbox>
    </object>
    <object>
        <name>rebar</name>
        <pose>Unspecified</pose>
        <truncated>0</truncated>
        <difficult>0</difficult>
        <bndbox>
            <xmin>831</xmin>
            <ymin>728</ymin>
            <xmax>988</xmax>
            <ymax>914</ymax>
        </bndbox>
    </object>
    <object>
        <name>rebar</name>
        <pose>Unspecified</pose>
        <truncated>0</truncated>
        <difficult>0</difficult>
        <bndbox>
            <xmin>734</xmin>
            <ymin>868</ymin>
            <xmax>908</xmax>
            <ymax>1008</ymax>
        </bndbox>
    </object>
    <object>
        <name>rebar</name>
        <pose>Unspecified</pose>
        <truncated>0</truncated>
        <difficult>0</difficult>
        <bndbox>
            <xmin>226</xmin>
            <ymin>892</ymin>
            <xmax>428</xmax>
            <ymax>1081</ymax>
        </bndbox>
    </object>
    <object>
        <name>rebar</name>
        <pose>Unspecified</pose>
        <truncated>0</truncated>
        <difficult>0</difficult>
        <bndbox>
            <xmin>424</xmin>
            <ymin>933</ymin>
            <xmax>614</xmax>
            <ymax>1102</ymax>
        </bndbox>
    </object>
    <object>
        <name>rebar</name>
        <pose>Unspecified</pose>
        <truncated>0</truncated>
        <difficult>0</difficult>
        <bndbox>
            <xmin>559</xmin>
            <ymin>1034</ymin>
            <xmax>742</xmax>
            <ymax>1225</ymax>
        </bndbox>
    </object>
    <object>
        <name>rebar</name>
        <pose>Unspecified</pose>
        <truncated>0</truncated>
        <difficult>0</difficult>
        <bndbox>
            <xmin>486</xmin>
            <ymin>1179</ymin>
            <xmax>664</xmax>
            <ymax>1355</ymax>
        </bndbox>
    </object>
    <object>
        <name>rebar</name>
        <pose>Unspecified</pose>
        <truncated>0</truncated>
        <difficult>0</difficult>
        <bndbox>
            <xmin>672</xmin>
            <ymin>1218</ymin>
            <xmax>855</xmax>
            <ymax>1391</ymax>
        </bndbox>
    </object>
    <object>
        <name>rebar</name>
        <pose>Unspecified</pose>
        <truncated>0</truncated>
        <difficult>0</difficult>
        <bndbox>
            <xmin>703</xmin>
            <ymin>1083</ymin>
            <xmax>906</xmax>
            <ymax>1271</ymax>
        </bndbox>
    </object>
    <object>
        <name>rebar</name>
        <pose>Unspecified</pose>
        <truncated>0</truncated>
        <difficult>0</difficult>
        <bndbox>
            <xmin>872</xmin>
            <ymin>943</ymin>
            <xmax>1038</xmax>
            <ymax>1121</ymax>
        </bndbox>
    </object>
    <object>
        <name>rebar</name>
        <pose>Unspecified</pose>
        <truncated>0</truncated>
        <difficult>0</difficult>
        <bndbox>
            <xmin>964</xmin>
            <ymin>813</ymin>
            <xmax>1123</xmax>
            <ymax>982</ymax>
        </bndbox>
    </object>
    <object>
        <name>rebar</name>
        <pose>Unspecified</pose>
        <truncated>0</truncated>
        <difficult>0</difficult>
        <bndbox>
            <xmin>1130</xmin>
            <ymin>806</ymin>
            <xmax>1296</xmax>
            <ymax>982</ymax>
        </bndbox>
    </object>
    <object>
        <name>rebar</name>
        <pose>Unspecified</pose>
        <truncated>0</truncated>
        <difficult>0</difficult>
        <bndbox>
            <xmin>1113</xmin>
            <ymin>982</ymin>
            <xmax>1282</xmax>
            <ymax>1129</ymax>
        </bndbox>
    </object>
    <object>
        <name>rebar</name>
        <pose>Unspecified</pose>
        <truncated>0</truncated>
        <difficult>0</difficult>
        <bndbox>
            <xmin>976</xmin>
            <ymin>1081</ymin>
            <xmax>1154</xmax>
            <ymax>1237</ymax>
        </bndbox>
    </object>
    <object>
        <name>rebar</name>
        <pose>Unspecified</pose>
        <truncated>0</truncated>
        <difficult>0</difficult>
        <bndbox>
            <xmin>908</xmin>
            <ymin>1208</ymin>
            <xmax>1072</xmax>
            <ymax>1377</ymax>
        </bndbox>
    </object>
    <object>
        <name>rebar</name>
        <pose>Unspecified</pose>
        <truncated>0</truncated>
        <difficult>0</difficult>
        <bndbox>
            <xmin>884</xmin>
            <ymin>1365</ymin>
            <xmax>1041</xmax>
            <ymax>1507</ymax>
        </bndbox>
    </object>
    <object>
        <name>rebar</name>
        <pose>Unspecified</pose>
        <truncated>0</truncated>
        <difficult>0</difficult>
        <bndbox>
            <xmin>1038</xmin>
            <ymin>1396</ymin>
            <xmax>1197</xmax>
            <ymax>1538</ymax>
        </bndbox>
    </object>
    <object>
        <name>rebar</name>
        <pose>Unspecified</pose>
        <truncated>0</truncated>
        <difficult>0</difficult>
        <bndbox>
            <xmin>1106</xmin>
            <ymin>1317</ymin>
            <xmax>1294</xmax>
            <ymax>1471</ymax>
        </bndbox>
    </object>
    <object>
        <name>rebar</name>
        <pose>Unspecified</pose>
        <truncated>0</truncated>
        <difficult>0</difficult>
        <bndbox>
            <xmin>1176</xmin>
            <ymin>1157</ymin>
            <xmax>1357</xmax>
            <ymax>1336</ymax>
        </bndbox>
    </object>
    <object>
        <name>rebar</name>
        <pose>Unspecified</pose>
        <truncated>0</truncated>
        <difficult>0</difficult>
        <bndbox>
            <xmin>1260</xmin>
            <ymin>1278</ymin>
            <xmax>1414</xmax>
            <ymax>1425</ymax>
        </bndbox>
    </object>
    <object>
        <name>rebar</name>
        <pose>Unspecified</pose>
        <truncated>0</truncated>
        <difficult>0</difficult>
        <bndbox>
            <xmin>1311</xmin>
            <ymin>1420</ymin>
            <xmax>1468</xmax>
            <ymax>1579</ymax>
        </bndbox>
    </object>
    <object>
        <name>rebar</name>
        <pose>Unspecified</pose>
        <truncated>0</truncated>
        <difficult>0</difficult>
        <bndbox>
            <xmin>1487</xmin>
            <ymin>1394</ymin>
            <xmax>1660</xmax>
            <ymax>1521</ymax>
        </bndbox>
    </object>
    <object>
        <name>rebar</name>
        <pose>Unspecified</pose>
        <truncated>0</truncated>
        <difficult>0</difficult>
        <bndbox>
            <xmin>1489</xmin>
            <ymin>1517</ymin>
            <xmax>1625</xmax>
            <ymax>1656</ymax>
        </bndbox>
    </object>
    <object>
        <name>rebar</name>
        <pose>Unspecified</pose>
        <truncated>0</truncated>
        <difficult>0</difficult>
        <bndbox>
            <xmin>1538</xmin>
            <ymin>1259</ymin>
            <xmax>1697</xmax>
            <ymax>1435</ymax>
        </bndbox>
    </object>
    <object>
        <name>rebar</name>
        <pose>Unspecified</pose>
        <truncated>0</truncated>
        <difficult>0</difficult>
        <bndbox>
            <xmin>1292</xmin>
            <ymin>1015</ymin>
            <xmax>1441</xmax>
            <ymax>1174</ymax>
        </bndbox>
    </object>
    <object>
        <name>rebar</name>
        <pose>Unspecified</pose>
        <truncated>0</truncated>
        <difficult>0</difficult>
        <bndbox>
            <xmin>1402</xmin>
            <ymin>1087</ymin>
            <xmax>1561</xmax>
            <ymax>1244</ymax>
        </bndbox>
    </object>
    <object>
        <name>rebar</name>
        <pose>Unspecified</pose>
        <truncated>0</truncated>
        <difficult>0</difficult>
        <bndbox>
            <xmin>1296</xmin>
            <ymin>842</ymin>
            <xmax>1441</xmax>
            <ymax>976</ymax>
        </bndbox>
    </object>
    <object>
        <name>rebar</name>
        <pose>Unspecified</pose>
        <truncated>0</truncated>
        <difficult>0</difficult>
        <bndbox>
            <xmin>1395</xmin>
            <ymin>912</ymin>
            <xmax>1538</xmax>
            <ymax>1068</ymax>
        </bndbox>
    </object>
    <object>
        <name>rebar</name>
        <pose>Unspecified</pose>
        <truncated>0</truncated>
        <difficult>0</difficult>
        <bndbox>
            <xmin>1468</xmin>
            <ymin>745</ymin>
            <xmax>1600</xmax>
            <ymax>914</ymax>
        </bndbox>
    </object>
    <object>
        <name>rebar</name>
        <pose>Unspecified</pose>
        <truncated>0</truncated>
        <difficult>0</difficult>
        <bndbox>
            <xmin>1583</xmin>
            <ymin>784</ymin>
            <xmax>1747</xmax>
            <ymax>953</ymax>
        </bndbox>
    </object>
    <object>
        <name>rebar</name>
        <pose>Unspecified</pose>
        <truncated>0</truncated>
        <difficult>0</difficult>
        <bndbox>
            <xmin>1616</xmin>
            <ymin>967</ymin>
            <xmax>1773</xmax>
            <ymax>1131</ymax>
        </bndbox>
    </object>
    <object>
        <name>rebar</name>
        <pose>Unspecified</pose>
        <truncated>0</truncated>
        <difficult>0</difficult>
        <bndbox>
            <xmin>1593</xmin>
            <ymin>1097</ymin>
            <xmax>1733</xmax>
            <ymax>1254</ymax>
        </bndbox>
    </object>
    <object>
        <name>rebar</name>
        <pose>Unspecified</pose>
        <truncated>0</truncated>
        <difficult>0</difficult>
        <bndbox>
            <xmin>1839</xmin>
            <ymin>1109</ymin>
            <xmax>1989</xmax>
            <ymax>1283</ymax>
        </bndbox>
    </object>
    <object>
        <name>rebar</name>
        <pose>Unspecified</pose>
        <truncated>0</truncated>
        <difficult>0</difficult>
        <bndbox>
            <xmin>1764</xmin>
            <ymin>1240</ymin>
            <xmax>1918</xmax>
            <ymax>1418</ymax>
        </bndbox>
    </object>
    <object>
        <name>rebar</name>
        <pose>Unspecified</pose>
        <truncated>0</truncated>
        <difficult>0</difficult>
        <bndbox>
            <xmin>1673</xmin>
            <ymin>1394</ymin>
            <xmax>1834</xmax>
            <ymax>1543</ymax>
        </bndbox>
    </object>
    <object>
        <name>rebar</name>
        <pose>Unspecified</pose>
        <truncated>0</truncated>
        <difficult>0</difficult>
        <bndbox>
            <xmin>1877</xmin>
            <ymin>1401</ymin>
            <xmax>2012</xmax>
            <ymax>1534</ymax>
        </bndbox>
    </object>
    <object>
        <name>rebar</name>
        <pose>Unspecified</pose>
        <truncated>0</truncated>
        <difficult>0</difficult>
        <bndbox>
            <xmin>2051</xmin>
            <ymin>1370</ymin>
            <xmax>2237</xmax>
            <ymax>1546</ymax>
        </bndbox>
    </object>
    <object>
        <name>rebar</name>
        <pose>Unspecified</pose>
        <truncated>0</truncated>
        <difficult>0</difficult>
        <bndbox>
            <xmin>2239</xmin>
            <ymin>1338</ymin>
            <xmax>2408</xmax>
            <ymax>1509</ymax>
        </bndbox>
    </object>
    <object>
        <name>rebar</name>
        <pose>Unspecified</pose>
        <truncated>0</truncated>
        <difficult>0</difficult>
        <bndbox>
            <xmin>2247</xmin>
            <ymin>1497</ymin>
            <xmax>2415</xmax>
            <ymax>1620</ymax>
        </bndbox>
    </object>
    <object>
        <name>rebar</name>
        <pose>Unspecified</pose>
        <truncated>0</truncated>
        <difficult>0</difficult>
        <bndbox>
            <xmin>2189</xmin>
            <ymin>1598</ymin>
            <xmax>2333</xmax>
            <ymax>1770</ymax>
        </bndbox>
    </object>
    <object>
        <name>rebar</name>
        <pose>Unspecified</pose>
        <truncated>0</truncated>
        <difficult>0</difficult>
        <bndbox>
            <xmin>1882</xmin>
            <ymin>899</ymin>
            <xmax>2037</xmax>
            <ymax>1078</ymax>
        </bndbox>
    </object>
    <object>
        <name>rebar</name>
        <pose>Unspecified</pose>
        <truncated>0</truncated>
        <difficult>0</difficult>
        <bndbox>
            <xmin>2024</xmin>
            <ymin>1023</ymin>
            <xmax>2196</xmax>
            <ymax>1213</ymax>
        </bndbox>
    </object>
    <object>
        <name>rebar</name>
        <pose>Unspecified</pose>
        <truncated>0</truncated>
        <difficult>0</difficult>
        <bndbox>
            <xmin>2133</xmin>
            <ymin>1102</ymin>
            <xmax>2295</xmax>
            <ymax>1261</ymax>
        </bndbox>
    </object>
</annotation>